circle_ooak/__init__
circle_ooak/agent_tool.py
circle_ooak/instance_agent.py
circle_ooak/secure_tool.py
circle_ooak/workflow_manager.py
circle_ooak-0.1.0.dist-info/METADATA
circle_ooak-0.1.0.dist-info/WHEEL
circle_ooak-0.1.0.dist-info/licenses/LICENSE.Apache
circle_ooak-0.1.0.dist-info/licenses/LICENSE.MIT
circle_ooak-0.1.0.dist-info/RECORD
