Metadata-Version: 2.4
Name: circle-ooak
Version: 0.1.0
Summary: OOAK: Object Oriented Agent Kit
Project-URL: Homepage, https://github.com/circlefin/circle-ooak
Author-email: Mira Belenkiy <mira.belenkiy@circle.com>
License-Expression: Apache-2.0
License-File: LICENSE.Apache
License-File: LICENSE.MIT
Classifier: Operating System :: OS Independent
Classifier: Programming Language :: Python :: 3
Requires-Python: >=3.10
Requires-Dist: openai
Requires-Dist: openai-agents==0.2.6
Requires-Dist: python-dotenv
Provides-Extra: dev
Requires-Dist: build; extra == 'dev'
Requires-Dist: pytest; extra == 'dev'
Requires-Dist: pytest-asyncio; extra == 'dev'
Requires-Dist: twine; extra == 'dev'
Provides-Extra: test
Requires-Dist: pytest; extra == 'test'
Requires-Dist: pytest-asyncio; extra == 'test'
